pushikoo_adapter_testgetter/__init__.py
pushikoo_adapter_testgetter/api.py
pushikoo_adapter_testgetter/config.py
pushikoo_adapter_testgetter/main.py
pushikoo_adapter_testgetter-0.1.2.dist-info/METADATA
pushikoo_adapter_testgetter-0.1.2.dist-info/WHEEL
pushikoo_adapter_testgetter-0.1.2.dist-info/entry_points.txt
pushikoo_adapter_testgetter-0.1.2.dist-info/licenses/LICENSE
pushikoo_adapter_testgetter-0.1.2.dist-info/RECORD
