Metadata-Version: 2.4
Name: pushikoo-adapter-testgetter
Version: 0.1.2
Summary: TestGetter for pushikoo-adapter development as a template.
Project-URL: Homepage, https://github.com/Pushikoo/pushikoo-adapter-testgetter
Author: Pushikoo
License-File: LICENSE
Classifier: Operating System :: OS Independent
Classifier: Programming Language :: Python :: 3
Requires-Python: >=3.10
Requires-Dist: loguru
Requires-Dist: pushikoo-interface>=0.2.0
Requires-Dist: requests
Provides-Extra: dev
Requires-Dist: pytest; extra == 'dev'
Requires-Dist: ruff; extra == 'dev'
